mcp_server_grist/__init__.py
mcp_server_grist/__main__.py
mcp_server_grist/client.py
mcp_server_grist/main.py
mcp_server_grist/models.py
mcp_server_grist/server.py
mcp_server_grist/types.py
mcp_server_grist/version.py
mcp_server_grist/tools/__init__.py
mcp_server_grist/tools/access.py
mcp_server_grist/tools/administration.py
mcp_server_grist/tools/attachments.py
mcp_server_grist/tools/export.py
mcp_server_grist/tools/navigation.py
mcp_server_grist/tools/queries.py
mcp_server_grist/tools/records.py
mcp_server_grist/tools/schema.py
mcp_server_grist/tools/utils.py
mcp_server_grist/tools/webhooks.py
mcp_server_grist-0.2.0.dist-info/licenses/LICENSE
mcp_server_grist-0.2.0.dist-info/METADATA
mcp_server_grist-0.2.0.dist-info/WHEEL
mcp_server_grist-0.2.0.dist-info/entry_points.txt
mcp_server_grist-0.2.0.dist-info/top_level.txt
mcp_server_grist-0.2.0.dist-info/RECORD
