Metadata-Version: 2.4
Name: mcp-server-grist
Version: 0.2.0
Summary: MCP server for Grist API integration
Author-email: MCP Contributors <info@example.com>
License-Expression: MIT
Project-URL: Homepage, https://github.com/nic01asFr/mcp-server-grist
Project-URL: Documentation, https://github.com/nic01asFr/mcp-server-grist/blob/main/README.md
Project-URL: Bug Reports, https://github.com/nic01asFr/mcp-server-grist/issues
Project-URL: Source, https://github.com/nic01asFr/mcp-server-grist
Classifier: Development Status :: 4 - Beta
Classifier: Intended Audience :: Developers
Classifier: Topic :: Software Development :: Libraries :: Python Modules
Classifier: Programming Language :: Python :: 3
Classifier: Programming Language :: Python :: 3.8
Classifier: Programming Language :: Python :: 3.9
Classifier: Programming Language :: Python :: 3.10
Classifier: Programming Language :: Python :: 3.11
Classifier: Operating System :: OS Independent
Classifier: Intended Audience :: Science/Research
Classifier: Intended Audience :: Information Technology
Classifier: Topic :: Scientific/Engineering :: Artificial Intelligence
Classifier: Topic :: Communications
Classifier: Topic :: Internet
Requires-Python: >=3.8
License-File: LICENSE
Requires-Dist: fastmcp>=2.8.0
Requires-Dist: mcp>=1.9.4
Requires-Dist: httpx>=0.24.0
Requires-Dist: pydantic>=2.0.0
Requires-Dist: python-dotenv>=1.0.0
Dynamic: license-file
